fixity/__init__.py
fixity/fixity.py
fixity/models.py
fixity/reporting.py
fixity/storage_service.py
fixity/utils.py
fixity-0.8.0.dist-info/LICENSE
fixity-0.8.0.dist-info/METADATA
fixity-0.8.0.dist-info/WHEEL
fixity-0.8.0.dist-info/entry_points.txt
fixity-0.8.0.dist-info/top_level.txt
fixity-0.8.0.dist-info/RECORD
